setup.py
python_random_en_us_diff.egg-info/PKG-INFO
python_random_en_us_diff.egg-info/SOURCES.txt
python_random_en_us_diff.egg-info/dependency_links.txt
python_random_en_us_diff.egg-info/not-zip-safe
python_random_en_us_diff.egg-info/top_level.txt
random_en_us_diff/__init__.py