Metadata-Version: 1.0
Name: python-random-en-us-diff
Version: 1.0.1
Summary: Cool simple Python module to get random difference between American and English languages. Isn't life so beautiful ?
Home-page: https://github.com/remaudcorentin-dev/python-random-en-us-diff
Author: Corentin Remaud
Author-email: remaudcorentin.dev@gmail.com
License: MIT
Platform: UNKNOWN
